uvi/__init__.py
uvi/cli.py
uvi-0.5.0.dist-info/LICENSE
uvi-0.5.0.dist-info/METADATA
uvi-0.5.0.dist-info/WHEEL
uvi-0.5.0.dist-info/entry_points.txt
uvi-0.5.0.dist-info/top_level.txt
uvi-0.5.0.dist-info/RECORD
