Metadata-Version: 2.2
Name: uvi
Version: 0.5.0
Summary: A python cookiecutter application to create a new python project that uses uv to manage its dependencies.
Author-email: Shane Holloman <shaneholloman@gmail.com>
Project-URL: Repository, https://github.com/shaneholloman/uvi
Project-URL: Documentation, https://shaneholloman.github.io/uvi/
Project-URL: Homepage, https://shaneholloman.github.io/uvi/
Keywords: cookiecutter,template,uv
Classifier: Development Status :: 4 - Beta
Classifier: Intended Audience :: Developers
Classifier: License :: OSI Approved :: MIT License
Classifier: Programming Language :: Python
Classifier: Programming Language :: Python :: 3
Classifier: Programming Language :: Python :: 3.10
Classifier: Programming Language :: Python :: 3.11
Classifier: Programming Language :: Python :: 3.12
Classifier: Programming Language :: Python :: 3.13
Classifier: Topic :: Software Development :: Libraries :: Python Modules
Classifier: Topic :: Software Development :: Code Generators
Requires-Python: <4.0,>=3.10
License-File: LICENSE
Requires-Dist: cookiecutter>=2.6.0
